{"0 9 * * *":{"A":{"natural":5,"correct":true,"note":"natural y claro"},"B":{"natural":5,"correct":true,"note":"natural y claro"},"C":{"natural":3,"correct":true,"note":"correcto pero omite 'todos los días'"},"D":{"natural":4,"correct":true,"note":"'09.00 h' algo formal pero válido"},"best":"A"},"30 9 * * *":{"A":{"natural":4,"correct":true,"note":"formal pero natural en Argentina"},"B":{"natural":3,"correct":true,"note":"omite 'todos los días'"},"C":{"natural":5,"correct":true,"note":"muy natural y explícito"},"D":{"natural":5,"correct":true,"note":"natural y claro"},"best":"D"},"0 14 * * *":{"A":{"natural":5,"correct":true,"note":"'14 h' muy natural en Argentina"},"B":{"natural":3,"correct":true,"note":"omite 'todos los días'"},"C":{"natural":4,"correct":true,"note":"'14.00 h' válido"},"D":{"natural":3,"correct":false,"note":"'a las 2' ambiguo; sugiere 2 a.m."},"best":"A"},"30 14 * * *":{"A":{"natural":5,"correct":true,"note":"natural y claro"},"B":{"natural":5,"correct":true,"note":"muy natural y explícito"},"C":{"natural":4,"correct":true,"note":"'14.30 h' válido"},"D":{"natural":3,"correct":false,"note":"'dos y media' sin 'tarde' ambiguo"},"best":"A"},"0 22 * * *":{"A":{"natural":4,"correct":true,"note":"'22.00 h' válido"},"B":{"natural":3,"correct":true,"note":"omite 'todos los días'"},"C":{"natural":5,"correct":true,"note":"natural y claro"},"D":{"natural":4,"correct":true,"note":"'a las 22' natural y claro"},"best":"C"},"0 0 * * *":{"A":{"natural":5,"correct":true,"note":"natural y claro"},"B":{"natural":3,"correct":true,"note":"'00.00 h' técnico pero correcto"},"C":{"natural":3,"correct":true,"note":"omite 'todos los días'"},"D":{"natural":5,"correct":true,"note":"natural y claro"},"best":"A"},"0 12 * * *":{"A":{"natural":4,"correct":true,"note":"'12.00 h' válido pero menos natural que mediodía"},"B":{"natural":5,"correct":true,"note":"natural y claro"},"C":{"natural":5,"correct":true,"note":"natural y claro"},"D":{"natural":3,"correct":true,"note":"omite 'todos los días'"},"best":"B"},"30 14 * * 1-5":{"A":{"natural":5,"correct":true,"note":"natural y claro"},"B":{"natural":4,"correct":true,"note":"orden invertido algo menos fluido"},"C":{"natural":5,"correct":true,"note":"natural y claro"},"D":{"natural":4,"correct":true,"note":"'dos y media' sin 'tarde' algo ambiguo"},"best":"C"},"0 8,20 * * *":{"A":{"natural":5,"correct":true,"note":"natural y explícito"},"B":{"natural":4,"correct":true,"note":"'08.00 h y 20.00 h' válido"},"C":{"natural":3,"correct":true,"note":"omite 'todos los días'"},"D":{"natural":3,"correct":false,"note":"'a.m./p.m.' poco usado en Argentina"},"best":"A"}}
